<?xml version="1.0" encoding="utf-8" ?><dwsync><file name=".htaccess" server="home697094325.1and1-data.host//./" local="3587123044" remote="3587123044" Dst="-1" /><file name="info.pl" server="home697094325.1and1-data.host//./" local="3587123044" remote="3587123044" Dst="-1" /><file name="info.php5" server="home697094325.1and1-data.host//./" local="3587123044" remote="3587123044" Dst="-1" /><file name="info.py" server="home697094325.1and1-data.host//./" local="3587123044" remote="3587123044" Dst="-1" /><file name="traffic.db" server="home697094325.1and1-data.host//./" local="3588293987" remote="3588293987" Dst="-1" /><file name="last_traffic" server="home697094325.1and1-data.host//./" local="3588293987" remote="3588293987" Dst="-1" /><file name="sftp.log.35.gz" server="home697094325.1and1-data.host//./" local="3587131715" remote="3587131715" Dst="-1" /><file name="access.log.36.1.gz" server="home697094325.1and1-data.host//./" local="3587425190" remote="3587425190" Dst="-1" /><file name="access.log.36.2.gz" server="home697094325.1and1-data.host//./" local="3587510598" remote="3587510598" Dst="-1" /><file name="access.log.36.3.gz" server="home697094325.1and1-data.host//./" local="3587600343" remote="3587600343" Dst="-1" /><file name="access.log.36.4.gz" server="home697094325.1and1-data.host//./" local="3587687215" remote="3587687215" Dst="-1" /><file name="access.log.36.5.gz" server="home697094325.1and1-data.host//./" local="3587771216" remote="3587771216" Dst="-1" /><file name="access.log.36.6.gz" server="home697094325.1and1-data.host//./" local="3587859245" remote="3587859245" Dst="-1" /><file name="access.log.36.7.gz" server="home697094325.1and1-data.host//./" local="3587945345" remote="3587945345" Dst="-1" /><file name="sftp.log.36.gz" server="home697094325.1and1-data.host//./" local="3587736078" remote="3587736078" Dst="-1" /><file name="access.log.35.gz" server="home697094325.1and1-data.host//./" local="3587340938" remote="3587340938" Dst="-1" /><file name="access.log.37.1.gz" server="home697094325.1and1-data.host//./" local="3588032971" remote="3588032971" Dst="-1" /><file name="access.log.37.2.gz" server="home697094325.1and1-data.host//./" local="3588118540" remote="3588118540" Dst="-1" /><file name="access.log.37.3.gz" server="home697094325.1and1-data.host//./" local="3588202948" remote="3588202948" Dst="-1" /><file name="access.log.37.4.gz" server="home697094325.1and1-data.host//./" local="3588289204" remote="3588289204" Dst="-1" /><file name="access.log.37.5" server="home697094325.1and1-data.host//./" local="3588331670" remote="3588331670" Dst="-1" /><file name="access.log.current" server="home697094325.1and1-data.host//./" local="3588295183" remote="3588295183" Dst="-1" /><file name="sftp.log" server="home697094325.1and1-data.host//./" local="3588331965" remote="3588331971" Dst="-1" /><file name="access.log.42.gz" server="home697094325.1and1-data.host//./" local="3591556723" remote="3591556723" Dst="-1" /><file name="access.log.43.gz" server="home697094325.1and1-data.host//./" local="3592179551" remote="3592179551" Dst="-1" /><file name="access.log.44.gz" server="home697094325.1and1-data.host//./" local="3592784759" remote="3592784759" Dst="-1" /><file name="access.log.45.gz" server="home697094325.1and1-data.host//./" local="3593392574" remote="3593392574" Dst="-1" /><file name="access.log.46.gz" server="home697094325.1and1-data.host//./" local="3593996287" remote="3593996287" Dst="-1" /><file name="access.log.47.gz" server="home697094325.1and1-data.host//./" local="3594600633" remote="3594600633" Dst="-1" /><file name="access.log.48.gz" server="home697094325.1and1-data.host//./" local="3595202334" remote="3595202334" Dst="-1" /><file name="access.log.49.1.gz" server="home697094325.1and1-data.host//./" local="3595294092" remote="3595294092" Dst="-1" /><file name="access.log.49.2.gz" server="home697094325.1and1-data.host//./" local="3595380970" remote="3595380970" Dst="-1" /><file name="access.log.49.3.gz" server="home697094325.1and1-data.host//./" local="3595466757" remote="3595466757" Dst="-1" /><file name="access.log.49.4.gz" server="home697094325.1and1-data.host//./" local="3595548759" remote="3595548759" Dst="-1" /><file name="access.log.49.5.gz" server="home697094325.1and1-data.host//./" local="3595633093" remote="3595633093" Dst="-1" /><file name="access.log.49.6.gz" server="home697094325.1and1-data.host//./" local="3595719673" remote="3595719673" Dst="-1" /><file name="access.log.49.7.gz" server="home697094325.1and1-data.host//./" local="3595805206" remote="3595805206" Dst="-1" /><file name="access.log.50.1.gz" server="home697094325.1and1-data.host//./" local="3595893537" remote="3595893537" Dst="-1" /><file name="access.log.50.2.gz" server="home697094325.1and1-data.host//./" local="3595981656" remote="3595981656" Dst="-1" /><file name="access.log.50.3.gz" server="home697094325.1and1-data.host//./" local="3596063337" remote="3596063337" Dst="-1" /><file name="access.log.50.4.gz" server="home697094325.1and1-data.host//./" local="3596158156" remote="3596158156" Dst="-1" /><file name="access.log.50.5" server="home697094325.1and1-data.host//./" local="3596173273" remote="3596173273" Dst="-1" /><file name="dav.log.47.gz" server="home697094325.1and1-data.host//./" local="3594427171" remote="3594427171" Dst="-1" /><file name="mail.log.44.gz" server="home697094325.1and1-data.host//./" local="3592573442" remote="3592573442" Dst="-1" /><file name="mail.log.45.gz" server="home697094325.1and1-data.host//./" local="3593117041" remote="3593117041" Dst="-1" /><file name="sftp.log.42.gz" server="home697094325.1and1-data.host//./" local="3591367189" remote="3591367189" Dst="-1" /><file name="sftp.log.43.gz" server="home697094325.1and1-data.host//./" local="3591970954" remote="3591970954" Dst="-1" /><file name="sftp.log.44.gz" server="home697094325.1and1-data.host//./" local="3592578851" remote="3592578851" Dst="-1" /><file name="sftp.log.45.gz" server="home697094325.1and1-data.host//./" local="3593184704" remote="3593184704" Dst="-1" /><file name="sftp.log.48.gz" server="home697094325.1and1-data.host//./" local="3594999234" remote="3594999234" Dst="-1" /><file name="sftp.log.49.gz" server="home697094325.1and1-data.host//./" local="3595379750" remote="3595379750" Dst="-1" /><file name="access.log.50.5.gz" server="home697094325.1and1-data.host//./" local="3596243495" remote="3596243495" Dst="-1" /><file name="access.log.50.6.gz" server="home697094325.1and1-data.host//./" local="3596329271" remote="3596329271" Dst="-1" /><file name="access.log.50.7" server="home697094325.1and1-data.host//./" local="3596402314" remote="3596402314" Dst="-1" /></dwsync>